s3prl_vc/__init__.py
s3prl_vc/bin/__init__.py
s3prl_vc/bin/compute_statistics.py
s3prl_vc/bin/create_histogram.py
s3prl_vc/bin/decode.py
s3prl_vc/bin/decode_downstream.py
s3prl_vc/bin/extract_spemb.py
s3prl_vc/bin/extract_upstream.py
s3prl_vc/bin/train.py
s3prl_vc/datasets/__init__.py
s3prl_vc/datasets/datasets.py
s3prl_vc/evaluate/__init__.py
s3prl_vc/evaluate/asr.py
s3prl_vc/evaluate/asv.py
s3prl_vc/evaluate/dtw_based.py
s3prl_vc/layers/__init__.py
s3prl_vc/layers/utils.py
s3prl_vc/losses/__init__.py
s3prl_vc/losses/l1_loss.py
s3prl_vc/losses/l2_loss.py
s3prl_vc/models/Taco2_AR.py
s3prl_vc/models/__init__.py
s3prl_vc/models/diffusion.py
s3prl_vc/models/diffsinger/__init__.py
s3prl_vc/models/diffsinger/denoiser.py
s3prl_vc/models/diffsinger/diffusion.py
s3prl_vc/schedulers/__init__.py
s3prl_vc/schedulers/schedulers.py
s3prl_vc/transform/__init__.py
s3prl_vc/transform/f0.py
s3prl_vc/transform/spectrogram.py
s3prl_vc/upstream/__init__.py
s3prl_vc/upstream/interface.py
s3prl_vc/upstream/whisper.py
s3prl_vc/upstream/ppg_sxliu/__init__.py
s3prl_vc/upstream/ppg_sxliu/e2e_asr_common.py
s3prl_vc/upstream/ppg_sxliu/encoders.py
s3prl_vc/upstream/ppg_sxliu/frontend.py
s3prl_vc/upstream/ppg_sxliu/log_mel.py
s3prl_vc/upstream/ppg_sxliu/model.py
s3prl_vc/upstream/ppg_sxliu/nets_utils.py
s3prl_vc/upstream/ppg_sxliu/ppg_sxliu.py
s3prl_vc/upstream/ppg_sxliu/stft.py
s3prl_vc/upstream/ppg_sxliu/utterance_mvn.py
s3prl_vc/upstream/ppg_sxliu/encoder/__init__.py
s3prl_vc/upstream/ppg_sxliu/encoder/attention.py
s3prl_vc/upstream/ppg_sxliu/encoder/conformer_encoder.py
s3prl_vc/upstream/ppg_sxliu/encoder/convolution.py
s3prl_vc/upstream/ppg_sxliu/encoder/embedding.py
s3prl_vc/upstream/ppg_sxliu/encoder/encoder.py
s3prl_vc/upstream/ppg_sxliu/encoder/encoder_layer.py
s3prl_vc/upstream/ppg_sxliu/encoder/layer_norm.py
s3prl_vc/upstream/ppg_sxliu/encoder/multi_layer_conv.py
s3prl_vc/upstream/ppg_sxliu/encoder/positionwise_feed_forward.py
s3prl_vc/upstream/ppg_sxliu/encoder/repeat.py
s3prl_vc-0.3.1.dist-info/LICENSE
s3prl_vc-0.3.1.dist-info/METADATA
s3prl_vc-0.3.1.dist-info/WHEEL
s3prl_vc-0.3.1.dist-info/entry_points.txt
s3prl_vc-0.3.1.dist-info/top_level.txt
s3prl_vc-0.3.1.dist-info/RECORD
